acs_explorer/__init__.py
acs_explorer/acs_explorer.py
acs_explorer-0.1.9.dist-info/LICENSE
acs_explorer-0.1.9.dist-info/METADATA
acs_explorer-0.1.9.dist-info/WHEEL
acs_explorer-0.1.9.dist-info/RECORD
