Metadata-Version: 2.1
Name: acs_explorer
Version: 0.1.9
Summary: A python package that helps user to search for and analyze ACS data.
Home-page: https://github.com/77889itsme/acs-explorer
License: MIT
Author: Yiqi Ling
Requires-Python: >=3.12,<4.0
Classifier: License :: OSI Approved :: MIT License
Classifier: Programming Language :: Python :: 3
Classifier: Programming Language :: Python :: 3.12
Project-URL: Documentation, https://acs-explorer.readthedocs.io
Project-URL: Repository, https://github.com/77889itsme/acs-explorer
